voliboli_sgqlc_types/__init__.py
voliboli_sgqlc_types/main.py
voliboli_sgqlc_types-1.10.dist-info/METADATA
voliboli_sgqlc_types-1.10.dist-info/WHEEL
voliboli_sgqlc_types-1.10.dist-info/top_level.txt
voliboli_sgqlc_types-1.10.dist-info/RECORD
