Metadata-Version: 2.1
Name: voliboli-sgqlc-types
Version: 1.10
Summary: Voliboli SGQLC Types
Author: Teodor Janez Podobnik
Author-email: teo.podobnik1234@gmail.com
License: MIT
Classifier: Programming Language :: Python :: 3
Classifier: License :: OSI Approved :: MIT License
Classifier: Operating System :: OS Independent
Requires-Dist: sgqlc
